odoo9_addon_account_move_line_product-9.0.1.0.0.99.dev6-py2.7-nspkg.pth
odoo9_addon_account_move_line_product-9.0.1.0.0.99.dev6.dist-info/DESCRIPTION.rst
odoo9_addon_account_move_line_product-9.0.1.0.0.99.dev6.dist-info/METADATA
odoo9_addon_account_move_line_product-9.0.1.0.0.99.dev6.dist-info/RECORD
odoo9_addon_account_move_line_product-9.0.1.0.0.99.dev6.dist-info/WHEEL
odoo9_addon_account_move_line_product-9.0.1.0.0.99.dev6.dist-info/metadata.json
odoo9_addon_account_move_line_product-9.0.1.0.0.99.dev6.dist-info/namespace_packages.txt
odoo9_addon_account_move_line_product-9.0.1.0.0.99.dev6.dist-info/top_level.txt
odoo_addons/account_move_line_product/README.rst
odoo_addons/account_move_line_product/__init__.py
odoo_addons/account_move_line_product/__openerp__.py
odoo_addons/account_move_line_product/i18n/account_move_line_product.pot
odoo_addons/account_move_line_product/i18n/ca.po
odoo_addons/account_move_line_product/i18n/de.po
odoo_addons/account_move_line_product/i18n/el_GR.po
odoo_addons/account_move_line_product/i18n/es.po
odoo_addons/account_move_line_product/i18n/es_ES.po
odoo_addons/account_move_line_product/i18n/eu.po
odoo_addons/account_move_line_product/i18n/fi.po
odoo_addons/account_move_line_product/i18n/fr.po
odoo_addons/account_move_line_product/i18n/fr_CH.po
odoo_addons/account_move_line_product/i18n/fr_FR.po
odoo_addons/account_move_line_product/i18n/gl.po
odoo_addons/account_move_line_product/i18n/hr.po
odoo_addons/account_move_line_product/i18n/hr_HR.po
odoo_addons/account_move_line_product/i18n/it.po
odoo_addons/account_move_line_product/i18n/nl.po
odoo_addons/account_move_line_product/i18n/nl_NL.po
odoo_addons/account_move_line_product/i18n/pt.po
odoo_addons/account_move_line_product/i18n/pt_BR.po
odoo_addons/account_move_line_product/i18n/ro.po
odoo_addons/account_move_line_product/i18n/ru.po
odoo_addons/account_move_line_product/i18n/sk.po
odoo_addons/account_move_line_product/i18n/sl.po
odoo_addons/account_move_line_product/i18n/tr.po
odoo_addons/account_move_line_product/i18n/tr_TR.po
odoo_addons/account_move_line_product/i18n/vi_VN.po
odoo_addons/account_move_line_product/i18n/zh_CN.po
odoo_addons/account_move_line_product/static/description/icon.png
odoo_addons/account_move_line_product/views/account_move_line_view.xml
